muramasa/__init__.py
muramasa/anomaly_detection.py
muramasa/feature_extraction.py
muramasa/utils.py
muramasa/data/addgene_6018.csv
muramasa_kyoto-0.7.0.dist-info/LICENSE
muramasa_kyoto-0.7.0.dist-info/METADATA
muramasa_kyoto-0.7.0.dist-info/WHEEL
muramasa_kyoto-0.7.0.dist-info/top_level.txt
muramasa_kyoto-0.7.0.dist-info/RECORD
