Metadata-Version: 2.1
Name: muramasa-kyoto
Version: 0.7.0
Summary: A package for plasmid DNA sequence anomaly detection
Home-page: https://gitlab.igem.org/2024/software-tools/kyoto
Author: Rei Suzawa
Author-email: reisuzawa.0725@gmail.com
Classifier: Programming Language :: Python :: 3
Classifier: License :: OSI Approved :: MIT License
Classifier: Operating System :: OS Independent
Requires-Python: >=3.6
License-File: LICENSE
Requires-Dist: numpy
Requires-Dist: pandas
Requires-Dist: scikit-learn
Requires-Dist: scipy
Requires-Dist: joblib
